contractsPY
