Metadata-Version: 2.1
Name: contractsPY
Version: 1.0.3
Summary: Python Business Transactions Library
Home-page: https://github.com/arzuhuseyn/contractsPY
Author: Arzu Huseynov
Author-email: hi@arzuh.me
License: MIT
Keywords: railway-oriented usecases transactions contracts
Platform: UNKNOWN
Classifier: Intended Audience :: Developers
Classifier: Topic :: Internet
Classifier: License :: OSI Approved :: MIT License
Classifier: Programming Language :: Python
Classifier: Programming Language :: Python :: 3.5
Classifier: Programming Language :: Python :: 3.6
Classifier: Programming Language :: Python :: 3.7
Classifier: Programming Language :: Python :: 3.8
Classifier: Programming Language :: Python :: 3.9
Classifier: Programming Language :: Python :: 3.10
